checkcel/__init__.py
checkcel/checkcel.py
checkcel/checkerator.py
checkcel/checkplate.py
checkcel/checkxtractor.py
checkcel/exceptions.py
checkcel/exits.py
checkcel/logs.py
checkcel/main.py
checkcel/validators.py
tests/__init__.py
tests/test_validate.py
tests/test_validate_datetime.py
tests/test_validate_gps.py
tests/test_validate_mail.py
tests/test_validate_number.py
tests/test_validate_params.py
tests/test_validate_regex.py
tests/test_validate_set.py
tests/test_validate_unique.py
checkcel-0.0.3.dist-info/LICENSE
checkcel-0.0.3.dist-info/METADATA
checkcel-0.0.3.dist-info/WHEEL
checkcel-0.0.3.dist-info/entry_points.txt
checkcel-0.0.3.dist-info/top_level.txt
checkcel-0.0.3.dist-info/RECORD
