Metadata-Version: 2.1
Name: checkcel
Version: 0.0.3
Summary: Generate and validate tabulated/spreadsheet files
Home-page: https://github.com/genouest/checkcel
Author: Mateo Boudet
Author-email: mateo.boudet@inrae.fr
License: MIT
Platform: Posix; MacOS X; Windows
Classifier: Intended Audience :: Developers
Classifier: License :: OSI Approved :: MIT License
Classifier: Operating System :: OS Independent
Classifier: Topic :: Scientific/Engineering
Classifier: Programming Language :: Python :: 3.7
License-File: LICENSE
Requires-Dist: openpyxl
Requires-Dist: odfpy
Requires-Dist: pandas
Requires-Dist: email-validator
Requires-Dist: pyyaml
Requires-Dist: requests
